src/__init__.py
src/allison_foster.py
ordinal_scale_stats-0.0.1.dist-info/LICENSE.md
ordinal_scale_stats-0.0.1.dist-info/METADATA
ordinal_scale_stats-0.0.1.dist-info/WHEEL
ordinal_scale_stats-0.0.1.dist-info/RECORD
