Metadata-Version: 2.1
Name: ordinal-scale-stats
Version: 0.0.1
Summary: Ordinal Scale Datasets statistics
License: MIT
Author: HackerSpace Trójmiasto
Requires-Python: >=3.10,<3.11
Classifier: License :: OSI Approved :: MIT License
Classifier: Programming Language :: Python :: 3
Classifier: Programming Language :: Python :: 3.10
Requires-Dist: black (>=23.3.0,<24.0.0)
Requires-Dist: flake8 (>=6.0.0,<7.0.0)
Requires-Dist: numpy (>=1.25.1,<2.0.0)
Requires-Dist: pandas (>=2.0.3,<3.0.0)
Requires-Dist: pytest (>=7.4.0,<8.0.0)
Requires-Dist: scipy (>=1.11.1,<2.0.0)
